oarepo_model_builder_cf/__init__.py
oarepo_model_builder_cf/builders.py
oarepo_model_builder_cf/components.py
oarepo_model_builder_cf/templates/__init__.py
oarepo_model_builder_cf/templates/record.py.jinja2
tests/__init__.py
tests/cf.yaml
tests/conftest.py
tests/test_custom_fields.py
tests/vocabularies.json
oarepo_model_builder_cf-4.0.8.dist-info/METADATA
oarepo_model_builder_cf-4.0.8.dist-info/WHEEL
oarepo_model_builder_cf-4.0.8.dist-info/entry_points.txt
oarepo_model_builder_cf-4.0.8.dist-info/top_level.txt
oarepo_model_builder_cf-4.0.8.dist-info/RECORD
