Metadata-Version: 2.1
Name: oarepo-model-builder-cf
Version: 4.0.8
Summary: "A model builder plugin for custom fields support"
Home-page: https://github.com/oarepo/oarepo-model-builder-cf
Author: Miroslav Simek
Author-email: simek.miroslav@techlib.cz
License: MIT
Keywords: invenio cf model builder
Platform: any
Classifier: Development Status :: 3 - Alpha
Requires-Python: >=3.9
Requires-Dist: oarepo-model-builder>=4.0.0
Provides-Extra: tests
Requires-Dist: pytest; extra == "tests"
